pocket_extraction/__init__.py
pocket_extraction/arguments.py
pocket_extraction/data_utils.py
pocket_extraction/extract_ligand.py
pocket_extraction/extract_ligand_and_pocket.py
pocket_extraction/extract_pocket.py
pocket_extraction/logger.py
pocket_extraction/non-LOI-blocklist.tsv
pocket_extraction/selection.py
pocket_extraction-0.1.7.dist-info/licenses/LICENSE
pocket_extraction-0.1.7.dist-info/METADATA
pocket_extraction-0.1.7.dist-info/WHEEL
pocket_extraction-0.1.7.dist-info/entry_points.txt
pocket_extraction-0.1.7.dist-info/top_level.txt
pocket_extraction-0.1.7.dist-info/RECORD
