Metadata-Version: 2.4
Name: pocket_extraction
Version: 0.1.7
Summary: A package for extracting ligands and binding pockets from PDB files
Author-email: Hanker <wu_2018@mail.ustc.edu.cn>
Project-URL: Homepage, https://github.com/HankerWu/pocket_extraction
Keywords: pocket extraction,ligand extraction,PDB processing
Classifier: Programming Language :: Python :: 3
Classifier: Operating System :: OS Independent
Requires-Python: >=3.7
License-File: LICENSE
Requires-Dist: biopython
Requires-Dist: rdkit
Requires-Dist: numpy
Dynamic: license-file
